Physical_formulas/Molecular_physics.py
Physical_formulas/Physics_warm.py
Physical_formulas/_init_.py
physical_formulas-1.0.dist-info/METADATA
physical_formulas-1.0.dist-info/WHEEL
physical_formulas-1.0.dist-info/top_level.txt
physical_formulas-1.0.dist-info/RECORD
