Metadata-Version: 2.2
Name: Physical_formulas
Version: 1.0
Summary: Physical formulas on the topics of heat and molecular physics
Author: svyt1310
Author-email: svyt7037@gmail.com
Dynamic: author
Dynamic: author-email
Dynamic: summary
